Metadata-Version: 2.1
Name: tento
Version: 8.3.20
Summary: UNKNOWN
Home-page: https://github.com/malododoma/tento
Author: malododoma
Author-email: malododoma@qq.com.cn
License: MIT
Project-URL: Documentation, https://tento.readthedocs.io
Project-URL: Source, https://github.com/malododoma/tento
Platform: UNKNOWN
Classifier: Development Status :: 5 - Production/Stable
Classifier: Intended Audience :: Developers
Classifier: Natural Language :: English
Classifier: License :: OSI Approved :: MIT License
